forallpeople/__init__.py
forallpeople/dimensions.py
forallpeople/environment.py
forallpeople/physical_helper_functions.py
forallpeople/tuplevector.py
forallpeople/environments/default.json
forallpeople/environments/electrical.json
forallpeople/environments/structural.json
forallpeople/environments/test_definitions.json
forallpeople/environments/thermal.json
forallpeople/environments/us_customary.json
forallpeople/tests/test_forallpeople.py
forallpeople/tests/test_tuplevector.py
forallpeople-2.7.0.dist-info/LICENSE
forallpeople-2.7.0.dist-info/LICENSE.TXT
forallpeople-2.7.0.dist-info/WHEEL
forallpeople-2.7.0.dist-info/METADATA
forallpeople-2.7.0.dist-info/RECORD
