Metadata-Version: 2.1
Name: forallpeople
Version: 2.7.0
Summary: The SI Units: "For all people, for all time"
Author-email: Connor Ferster <connorferster@structuralpython.com>
Classifier: License :: OSI Approved :: Apache Software License
Requires-Dist: black >= 22.3.0 ; extra == "dev"
Requires-Dist: sphinx ; extra == "doc"
Requires-Dist: nbsphinx ; extra == "doc"
Requires-Dist: pydata-sphinx-theme ; extra == "doc"
Requires-Dist: pytest-cov ; extra == "test"
Project-URL: Documentation, https://connorferster.github.io/forallpeople
Project-URL: Home, https://github.com/connorferster/forallpeople
Provides-Extra: dev
Provides-Extra: doc
Provides-Extra: test
